ssm_analyze/__init__.py
ssm_analyze/start_gui.py
ssm_analyze/gui/__init__.py
ssm_analyze/gui/qjsonmodel.py
ssm_analyze/gui/qt.py
ssm_analyze/gui/utils.py
ssm_analyze/gui/window.py
ssm_analyze/gui/img/icon.png
ssm_analyze/gui/widgets/__init__.py
ssm_analyze/gui/widgets/components.py
ssm_analyze/gui/widgets/dataset_browser.py
ssm_analyze/gui/widgets/meta.py
ssm_analyze/gui/widgets/plots.py
ssm_analyze/gui/widgets/shell.py
ssm_analyze/gui/widgets/sliders.py
ssm_analyze/sample_data/.DS_Store
ssm_analyze/sample_data/__init__.py
ssm_analyze/sample_data/data/.DS_Store
ssm_analyze/sample_data/data/2018-09-10/#001_scan_08-13-41/benders_position_x_set_index0_set_index1_set.dat
ssm_analyze/sample_data/data/2018-09-10/#001_scan_08-13-41/scan.png
ssm_analyze/sample_data/data/2018-09-10/#001_scan_08-13-41/scan0.mat
ssm_analyze/sample_data/data/2018-09-10/#001_scan_08-13-41/snapshot.json
ssm_analyze/sample_data/data/2018-09-10/#019_td_cap_13-50-12/benders_position_z_set_index0_set_index1_set.dat
ssm_analyze/sample_data/data/2018-09-10/#019_td_cap_13-50-12/snapshot.json
ssm_analyze/sample_data/data/2018-09-10/#019_td_cap_13-50-12/td_cap.png
ssm_analyze/sample_data/data/2018-09-10/#019_td_cap_13-50-12/td_cap0.mat
ssm_analyze/sample_data/data/2018-09-10/#031_scan_15-15-14/benders_position_x_set_index0_set_index1_set.dat
ssm_analyze/sample_data/data/2018-09-10/#031_scan_15-15-14/scan.png
ssm_analyze/sample_data/data/2018-09-10/#031_scan_15-15-14/scan0.mat
ssm_analyze/sample_data/data/2018-09-10/#031_scan_15-15-14/snapshot.json
ssm_analyze/sample_data/data/2018-09-10/#035_scan_16-29-55/benders_position_y_set_index0_set_index1_set.dat
ssm_analyze/sample_data/data/2018-09-10/#035_scan_16-29-55/scan.png
ssm_analyze/sample_data/data/2018-09-10/#035_scan_16-29-55/scan0.mat
ssm_analyze/sample_data/data/2018-09-10/#035_scan_16-29-55/snapshot.json
ssm_analyze/sample_data/data/2018-09-14/#001_td_cap_06-44-32/benders_position_z_set_index0_set_index1_set.dat
ssm_analyze-0.2.6.dist-info/LICENSE
ssm_analyze-0.2.6.dist-info/METADATA
ssm_analyze-0.2.6.dist-info/WHEEL
ssm_analyze-0.2.6.dist-info/entry_points.txt
ssm_analyze-0.2.6.dist-info/top_level.txt
ssm_analyze-0.2.6.dist-info/RECORD
