Metadata-Version: 2.1
Name: ssm-analyze
Version: 0.2.6
Summary: Analysis GUI for scanning SQUID microscopy
Home-page: https://github.com/loganbvh/ssm_analyze
Author: Logan Bishop-Van Horn
Author-email: logan.bvh@gmail.com
License: MIT
Keywords: scanning SQUID microscopy
Platform: Linux
Platform: Mac OSX
Platform: Unix
Platform: Windows
Classifier: Development Status :: 4 - Beta
Classifier: Intended Audience :: Science/Research
Classifier: License :: OSI Approved :: MIT License
Classifier: Operating System :: MacOS
Classifier: Operating System :: POSIX
Classifier: Operating System :: Unix
Classifier: Operating System :: Microsoft :: Windows
Classifier: Programming Language :: Python
Classifier: Programming Language :: Python :: 3.6
Classifier: Programming Language :: Python :: 3.7
Classifier: Programming Language :: Python :: 3.8
Classifier: Programming Language :: Python :: 3.9
Classifier: Topic :: Scientific/Engineering
Classifier: Topic :: Scientific/Engineering :: Physics
Requires-Python: >=3.6
Requires-Dist: h5py
Requires-Dist: ipykernel
Requires-Dist: ipython
Requires-Dist: jupyter
Requires-Dist: jupyter-console
Requires-Dist: matplotlib
Requires-Dist: numpy
Requires-Dist: pint
Requires-Dist: PyQt5
Requires-Dist: pyqtgraph
Requires-Dist: qcodes
Requires-Dist: qtpy
Requires-Dist: scipy
